MANIFEST.in
README.rst
setup.py
ckanext/__init__.py
ckanext/hdx_service_checker/__init__.py
ckanext/hdx_service_checker/checker.py
ckanext/hdx_service_checker/plugin.py
ckanext/hdx_service_checker/actions/__init__.py
ckanext/hdx_service_checker/actions/authorize.py
ckanext/hdx_service_checker/actions/get.py
ckanext/hdx_service_checker/checks/__init__.py
ckanext/hdx_service_checker/checks/checks.py
ckanext/hdx_service_checker/config/config.json
ckanext/hdx_service_checker/controllers/__init__.py
ckanext/hdx_service_checker/controllers/checks_controller.py
ckanext/hdx_service_checker/exceptions/__init__.py
ckanext/hdx_service_checker/templates/result_item.html
ckanext/hdx_service_checker/templates/show_check_results.html
ckanext/hdx_service_checker/tests/__init__.py
ckanext/hdx_service_checker/tests/test_plugin.py
ckanext_hdx_service_checker.egg-info/PKG-INFO
ckanext_hdx_service_checker.egg-info/SOURCES.txt
ckanext_hdx_service_checker.egg-info/dependency_links.txt
ckanext_hdx_service_checker.egg-info/entry_points.txt
ckanext_hdx_service_checker.egg-info/pbr.json
ckanext_hdx_service_checker.egg-info/top_level.txt