Metadata-Version: 1.1
Name: ckanext-hdx-service-checker
Version: 0.0.8
Summary: Customizable extension for checking the status of the network services that CKAN depends upon
Home-page: https://github.com/alexandru-m-g/ckanext-hdx_service_checker
Author: alexandru-m-g
Author-email: UNKNOWN
License: AGPL
Keywords: CKAN checker network services
Platform: UNKNOWN
Classifier: Development Status :: 4 - Beta
Classifier: License :: OSI Approved :: GNU Affero General Public License v3 or later (AGPLv3+)
Classifier: Programming Language :: Python :: 2.7
